{
    "forge_marker" : 1, 
    "defaults" : {
        "textures" : {
            "up" : "chargepads:blocks/healthpad_3_off", 
            "down" : "chargepads:blocks/pad_3_down", 
            "side" : "chargepads:blocks/pad_3_side"
        },
        "model" : "chargepads:topdown"
    }, 
    "variants" : {
        "normal" : [{
                
            }], 
        "inventory" : [{
                "transform" : "forge:default-block"
            }], 
        "facing" : {
            "down" : {
                "x" : 180
            }, 
            "up" : {
                
            }, 
            "north" : {
                "x" : 90
            }, 
            "south" : {
                "x" : 270
            }, 
            "west" : {
                "x" : 90, 
                "y" : 270
            }, 
            "east" : {
                "x" : 90, 
                "y" : 90
            }
        }, 
        "charge" : {
            "true" : {
                "textures" : {
                    "up" : "chargepads:blocks/healthpad_3_on"
                }
            }, 
            "false" : {
                
            }
        }
    }
}